{
  "id": "paper2-mini-telugu-01",
  "title": "Telugu Mini-Test - Sandhulu and Samaasaalu - Test 1",
  "type": "Mini-Test",
  "conductingBody": "Central Board of Secondary Education",
  "duration": 30,
  "totalMarks": 30,
  "totalQuestions": 30,
  "negativeMarking": false,
  "marksPerQuestion": 1,
  "instructions": [
    "This test comprises 30 questions, each carrying 1 mark.",
    "All questions are compulsory. There is no negative marking for wrong answers.",
    "The exam duration is 30 minutes.",
    "The timer will start as soon as you click 'Start Test'. The test will auto-submit when the timer reaches 00:00:00.",
    "Use the question palette on the right to navigate directly to any question.",
    "Click 'Save & Next' to save your answer and move to the next question. Answers are NOT saved automatically.",
    "Use 'Mark for Review & Next' to flag a question for later review. If you have answered it, the answer will still be counted.",
    "Use 'Clear Response' to deselect your chosen option for the current question.",
    "You can switch between sections at any time using the section tabs in the header.",
    "Do not refresh or close the browser window during the exam — your progress is saved but it is not recommended.",
    "Click 'Submit' to end the exam before the timer expires. A confirmation screen will appear."
  ],
  "sections": [
    {
      "id": "telugu",
      "name": "Telugu",
      "shortName": "Telugu",
      "questionCount": 30,
      "startIndex": 0
    }
  ],
  "questions": [
    {
      "id": "q1",
      "sectionId": "telugu",
      "globalIndex": 0,
      "text": "\"రాముడు + ఆలయం\" కలిసినప్పుడు సరైన సవర్ణదీర్ఘ సంధి రూపం ఏది?",
      "options": [
        {
          "key": "A",
          "text": "రాముఆలయం"
        },
        {
          "key": "B",
          "text": "రామూడాలయం"
        },
        {
          "key": "C",
          "text": "రాముదాలయం"
        },
        {
          "key": "D",
          "text": "రాముడాలయం"
        }
      ],
      "correctAnswer": "D",
      "explanation": "ఉకారం తరువాత అకారం వచ్చినప్పుడు సందర్భానుసారం దీర్ఘ స్వర ప్రభావంతో \"రాముడాలయం\" రూపం ఏర్పడుతుంది."
    },
    {
      "id": "q2",
      "sectionId": "telugu",
      "globalIndex": 1,
      "text": "\"మహా + ఇంద్రుడు\" అనే పదాల కలయికకు సరైన గుణసంధి రూపం ఏది?",
      "options": [
        {
          "key": "A",
          "text": "మహేంద్రుడు"
        },
        {
          "key": "B",
          "text": "మహైంద్రుడు"
        },
        {
          "key": "C",
          "text": "మహింద్రుడు"
        },
        {
          "key": "D",
          "text": "మహేంద్రం"
        }
      ],
      "correctAnswer": "A",
      "explanation": "అకారం తరువాత ఇకారం వచ్చినప్పుడు గుణసంధిలో \"ఏ\" ధ్వని ఏర్పడి \"మహేంద్రుడు\" అవుతుంది."
    },
    {
      "id": "q3",
      "sectionId": "telugu",
      "globalIndex": 2,
      "text": "\"దేవ + ఐశ్వర్యం\" కలిసినప్పుడు సాధారణ వృద్ధి సంధి రూపం ఏది?",
      "options": [
        {
          "key": "A",
          "text": "దేవేశ్వర్యం"
        },
        {
          "key": "B",
          "text": "దైవశ్వర్యం"
        },
        {
          "key": "C",
          "text": "దేవైశ్వర్యం"
        },
        {
          "key": "D",
          "text": "దేవశ్వర్యం"
        }
      ],
      "correctAnswer": "B",
      "explanation": "అకారం తరువాత ఐకారం వచ్చినప్పుడు వృద్ధి సంధి ప్రకారం \"ఐ\" ధ్వని ఏర్పడి \"దైవశ్వర్యం\" అవుతుంది."
    },
    {
      "id": "q4",
      "sectionId": "telugu",
      "globalIndex": 3,
      "text": "\"సత్ + జనుడు\" కలిసినప్పుడు ఏర్పడే సంధి రూపం ఏది?",
      "options": [
        {
          "key": "A",
          "text": "సజ్జనుడు"
        },
        {
          "key": "B",
          "text": "సత్జనుడు"
        },
        {
          "key": "C",
          "text": "సద్జనుడు"
        },
        {
          "key": "D",
          "text": "సజనుడు"
        }
      ],
      "correctAnswer": "A",
      "explanation": "త్ తరువాత జ ధ్వని వచ్చినప్పుడు ధ్వని మార్పుతో \"సజ్జనుడు\" అనే రూపం స్థిరపడింది."
    },
    {
      "id": "q5",
      "sectionId": "telugu",
      "globalIndex": 4,
      "text": "\"వాక్ + మయం\" అనే పదాల కలయికకు సరైన రూపం ఏది?",
      "options": [
        {
          "key": "A",
          "text": "వాగ్మయం"
        },
        {
          "key": "B",
          "text": "వాక్మయం"
        },
        {
          "key": "C",
          "text": "వాచ్మయం"
        },
        {
          "key": "D",
          "text": "వాక్యమయం"
        }
      ],
      "correctAnswer": "A",
      "explanation": "క్ తరువాత మ ధ్వని వచ్చినప్పుడు క్ గ్ గా మారి \"వాగ్మయం\" రూపం ఏర్పడుతుంది."
    },
    {
      "id": "q6",
      "sectionId": "telugu",
      "globalIndex": 5,
      "text": "\"తత్ + రూపం\" కలిసినప్పుడు సరైన రూపం ఏది?",
      "options": [
        {
          "key": "A",
          "text": "తత్రూపం"
        },
        {
          "key": "B",
          "text": "తద్రూపం"
        },
        {
          "key": "C",
          "text": "తతురూపం"
        },
        {
          "key": "D",
          "text": "తరూపం"
        }
      ],
      "correctAnswer": "B",
      "explanation": "తత్ అనే పదాంత ధ్వని తరువాత ర వచ్చినప్పుడు త్ ద్ గా మారి \"తద్రూపం\" అవుతుంది."
    },
    {
      "id": "q7",
      "sectionId": "telugu",
      "globalIndex": 6,
      "text": "\"లోక + ఉపకారం\" కలిసినప్పుడు సరైన సంధి రూపం ఏది?",
      "options": [
        {
          "key": "A",
          "text": "లోకోపకారం"
        },
        {
          "key": "B",
          "text": "లోకుపకారం"
        },
        {
          "key": "C",
          "text": "లోకాపకారం"
        },
        {
          "key": "D",
          "text": "లోకౌపకారం"
        }
      ],
      "correctAnswer": "A",
      "explanation": "అకారం తరువాత ఉకారం వచ్చినప్పుడు గుణసంధి ద్వారా \"ఓ\" ఏర్పడి \"లోకోపకారం\" అవుతుంది."
    },
    {
      "id": "q8",
      "sectionId": "telugu",
      "globalIndex": 7,
      "text": "\"సూర్య + ఉదయం\" కలయికకు సరైన రూపం ఏది?",
      "options": [
        {
          "key": "A",
          "text": "సూర్యుదయం"
        },
        {
          "key": "B",
          "text": "సూర్యోదయం"
        },
        {
          "key": "C",
          "text": "సూర్యౌదయం"
        },
        {
          "key": "D",
          "text": "సూర్యాదయం"
        }
      ],
      "correctAnswer": "B",
      "explanation": "అకారం తరువాత ఉకారం వచ్చినప్పుడు \"ఓ\" ధ్వని ఏర్పడి \"సూర్యోదయం\" అవుతుంది."
    },
    {
      "id": "q9",
      "sectionId": "telugu",
      "globalIndex": 8,
      "text": "\"రాజ + ఋషి\" కలిసినప్పుడు సాంప్రదాయక రూపం ఏది?",
      "options": [
        {
          "key": "A",
          "text": "రాజర్షి"
        },
        {
          "key": "B",
          "text": "రాజార్షి"
        },
        {
          "key": "C",
          "text": "రాజృషి"
        },
        {
          "key": "D",
          "text": "రాజరుషి"
        }
      ],
      "correctAnswer": "A",
      "explanation": "అకారం తరువాత ఋకారం వచ్చినప్పుడు గుణ ప్రభావంతో \"అర్\" ధ్వని ఏర్పడి \"రాజర్షి\" అవుతుంది."
    },
    {
      "id": "q10",
      "sectionId": "telugu",
      "globalIndex": 9,
      "text": "\"సమ్యక్ + జ్ఞానం\" కలిసినప్పుడు సరైన రూపం ఏది?",
      "options": [
        {
          "key": "A",
          "text": "సమ్యక్ జ్ఞానం"
        },
        {
          "key": "B",
          "text": "సమ్యజ్ఞానం"
        },
        {
          "key": "C",
          "text": "సమ్యగ్గ్ఞానం"
        },
        {
          "key": "D",
          "text": "సమ్యక్షానం"
        }
      ],
      "correctAnswer": "B",
      "explanation": "క్ తరువాత జ్ఞ ధ్వని వచ్చినప్పుడు ధ్వని మార్పుతో \"సమ్యజ్ఞానం\" రూపం ఏర్పడుతుంది."
    },
    {
      "id": "q11",
      "sectionId": "telugu",
      "globalIndex": 10,
      "text": "రెండు పదాలు కలిసినప్పుడు మధ్యలో ధ్వని మార్పు జరగడాన్ని ఏమంటారు?",
      "options": [
        {
          "key": "A",
          "text": "విభక్తి"
        },
        {
          "key": "B",
          "text": "సంధి"
        },
        {
          "key": "C",
          "text": "ప్రత్యయం"
        },
        {
          "key": "D",
          "text": "ఉపసర్గ"
        }
      ],
      "correctAnswer": "B",
      "explanation": "పదాల కలయికలో స్వర లేదా వ్యంజన ధ్వనుల్లో మార్పు జరిగితే దాన్ని సంధి అంటారు."
    },
    {
      "id": "q12",
      "sectionId": "telugu",
      "globalIndex": 11,
      "text": "స్వరంతో ముగిసిన పదం, స్వరంతో మొదలైన పదంతో కలిసినప్పుడు జరిగే సంధి సాధారణంగా ఏది?",
      "options": [
        {
          "key": "A",
          "text": "అచ్చుసంధి"
        },
        {
          "key": "B",
          "text": "హల్లుసంధి"
        },
        {
          "key": "C",
          "text": "లోపసంధి మాత్రమే"
        },
        {
          "key": "D",
          "text": "ద్వంద్వ సమాసం"
        }
      ],
      "correctAnswer": "A",
      "explanation": "రెండు స్వరాలు కలిసినప్పుడు స్వర మార్పు ప్రధానంగా ఉండే సంధిని అచ్చుసంధి అంటారు."
    },
    {
      "id": "q13",
      "sectionId": "telugu",
      "globalIndex": 12,
      "text": "\"అ\" మరియు \"ఇ\" కలిసినప్పుడు గుణసంధిలో సాధారణంగా ఏ స్వరం ఏర్పడుతుంది?",
      "options": [
        {
          "key": "A",
          "text": "ఆ"
        },
        {
          "key": "B",
          "text": "ఏ"
        },
        {
          "key": "C",
          "text": "ఓ"
        },
        {
          "key": "D",
          "text": "ఐ"
        }
      ],
      "correctAnswer": "B",
      "explanation": "గుణసంధి నియమంలో అ లేదా ఆ తరువాత ఇ లేదా ఈ వచ్చినప్పుడు \"ఏ\" ఏర్పడుతుంది."
    },
    {
      "id": "q14",
      "sectionId": "telugu",
      "globalIndex": 13,
      "text": "\"అ\" మరియు \"ఉ\" కలిసినప్పుడు గుణసంధిలో సాధారణంగా ఏ స్వరం ఏర్పడుతుంది?",
      "options": [
        {
          "key": "A",
          "text": "ఏ"
        },
        {
          "key": "B",
          "text": "ఓ"
        },
        {
          "key": "C",
          "text": "ఐ"
        },
        {
          "key": "D",
          "text": "ఔ"
        }
      ],
      "correctAnswer": "B",
      "explanation": "అ లేదా ఆ తరువాత ఉ లేదా ఊ వచ్చినప్పుడు గుణసంధి ప్రకారం \"ఓ\" ధ్వని ఏర్పడుతుంది."
    },
    {
      "id": "q15",
      "sectionId": "telugu",
      "globalIndex": 14,
      "text": "\"పర + ఉపకారం\" కలిసిన సరైన రూపం ఏది?",
      "options": [
        {
          "key": "A",
          "text": "పరోపకారం"
        },
        {
          "key": "B",
          "text": "పరూపకారం"
        },
        {
          "key": "C",
          "text": "పరాపకారం"
        },
        {
          "key": "D",
          "text": "పరైపకారం"
        }
      ],
      "correctAnswer": "A",
      "explanation": "అకారం తరువాత ఉకారం రావడంతో గుణసంధి ద్వారా \"పరోపకారం\" అవుతుంది."
    },
    {
      "id": "q16",
      "sectionId": "telugu",
      "globalIndex": 15,
      "text": "\"రాజు యొక్క కుమారుడు\" అనే భావాన్ని ఒక పదంగా చెప్పే సమాసం ఏది?",
      "options": [
        {
          "key": "A",
          "text": "రాజకుమారుడు"
        },
        {
          "key": "B",
          "text": "రాజూ కుమారుడు"
        },
        {
          "key": "C",
          "text": "కుమారరాజు"
        },
        {
          "key": "D",
          "text": "రాజకుమారం"
        }
      ],
      "correctAnswer": "A",
      "explanation": "\"రాజు యొక్క కుమారుడు\" అనే షష్ఠీ సంబంధం ఉండడం వల్ల ఇది తత్పురుష సమాసానికి ఉదాహరణ."
    },
    {
      "id": "q17",
      "sectionId": "telugu",
      "globalIndex": 16,
      "text": "\"నీలం అయిన కమలం\" అనే భావాన్ని తెలిపే సమాస పదం ఏది?",
      "options": [
        {
          "key": "A",
          "text": "నీలకమలం"
        },
        {
          "key": "B",
          "text": "కమలనీలం"
        },
        {
          "key": "C",
          "text": "నీలం కమలం"
        },
        {
          "key": "D",
          "text": "నీలకమలాలు"
        }
      ],
      "correctAnswer": "A",
      "explanation": "విశేషణం \"నీలం\" మరియు విశేష్యం \"కమలం\" కలిసినప్పుడు కర్మధారయ సమాసం అవుతుంది."
    },
    {
      "id": "q18",
      "sectionId": "telugu",
      "globalIndex": 17,
      "text": "\"తల్లి మరియు తండ్రి\" అనే భావాన్ని తెలిపే సమాస పదం ఏది?",
      "options": [
        {
          "key": "A",
          "text": "తల్లిదండ్రులు"
        },
        {
          "key": "B",
          "text": "తల్లితండ్రి"
        },
        {
          "key": "C",
          "text": "తండ్రితల్లి"
        },
        {
          "key": "D",
          "text": "తల్లిదండ్రి"
        }
      ],
      "correctAnswer": "A",
      "explanation": "రెండు సమాన ప్రాధాన్యం గల పదాలు కలిసినందున ఇది ద్వంద్వ సమాసం."
    },
    {
      "id": "q19",
      "sectionId": "telugu",
      "globalIndex": 18,
      "text": "\"మూడు లోకాలు\" అనే భావానికి సరైన సమాస పదం ఏది?",
      "options": [
        {
          "key": "A",
          "text": "త్రిలోకం"
        },
        {
          "key": "B",
          "text": "లోకత్రయం కాదు"
        },
        {
          "key": "C",
          "text": "మూడులోకం"
        },
        {
          "key": "D",
          "text": "లోకమూడు"
        }
      ],
      "correctAnswer": "A",
      "explanation": "సంఖ్యతో కూడిన భావం ఒక పదంగా వచ్చినప్పుడు ద్విగు సమాసం అవుతుంది; \"త్రిలోకం\" అలాంటి రూపం."
    },
    {
      "id": "q20",
      "sectionId": "telugu",
      "globalIndex": 19,
      "text": "\"పీతాంబరుడు\" అనే పదం ఏ సమాసానికి ఉదాహరణ?",
      "options": [
        {
          "key": "A",
          "text": "ద్వంద్వ సమాసం"
        },
        {
          "key": "B",
          "text": "బహువ్రీహి సమాసం"
        },
        {
          "key": "C",
          "text": "అవ్యయీభావ సమాసం"
        },
        {
          "key": "D",
          "text": "ద్విగు సమాసం"
        }
      ],
      "correctAnswer": "B",
      "explanation": "పీతం అంబరం కలవాడు అనే బాహ్య వ్యక్తిని సూచించడం వల్ల ఇది బహువ్రీహి సమాసం."
    },
    {
      "id": "q21",
      "sectionId": "telugu",
      "globalIndex": 20,
      "text": "\"యథాశక్తి\" అనే పదం ఏ సమాసానికి ఉదాహరణ?",
      "options": [
        {
          "key": "A",
          "text": "అవ్యయీభావ సమాసం"
        },
        {
          "key": "B",
          "text": "ద్వంద్వ సమాసం"
        },
        {
          "key": "C",
          "text": "కర్మధారయ సమాసం"
        },
        {
          "key": "D",
          "text": "బహువ్రీహి సమాసం"
        }
      ],
      "correctAnswer": "A",
      "explanation": "అవ్యయం ముందు వచ్చి మొత్తం పదాన్ని అవ్యయార్థంలో నిలబెడితే అవ్యయీభావ సమాసం అవుతుంది."
    },
    {
      "id": "q22",
      "sectionId": "telugu",
      "globalIndex": 21,
      "text": "\"గ్రామవాసి\" అనే పదం ఏ భావాన్ని తెలుపుతుంది?",
      "options": [
        {
          "key": "A",
          "text": "గ్రామంలో నివసించేవాడు"
        },
        {
          "key": "B",
          "text": "గ్రామం వంటి వాసి"
        },
        {
          "key": "C",
          "text": "గ్రామం మరియు వాసి"
        },
        {
          "key": "D",
          "text": "గ్రామం లేని వాసి"
        }
      ],
      "correctAnswer": "A",
      "explanation": "\"గ్రామంలో వాసి\" అనే స్థాన సంబంధం ఉండడం వల్ల ఇది తత్పురుష భావం."
    },
    {
      "id": "q23",
      "sectionId": "telugu",
      "globalIndex": 22,
      "text": "\"చంద్రబింబం\" అనే పదంలో సమాస భావం ఏది?",
      "options": [
        {
          "key": "A",
          "text": "చంద్రుని వంటి బింబం"
        },
        {
          "key": "B",
          "text": "చంద్రుడు మరియు బింబం"
        },
        {
          "key": "C",
          "text": "చంద్రుడు లేని బింబం"
        },
        {
          "key": "D",
          "text": "బింబం యొక్క చంద్రుడు"
        }
      ],
      "correctAnswer": "A",
      "explanation": "ఉపమాన భావంతో ఒక పదం మరొక పదాన్ని వివరించినప్పుడు కర్మధారయ సమాసంగా చూడవచ్చు."
    },
    {
      "id": "q24",
      "sectionId": "telugu",
      "globalIndex": 23,
      "text": "సమాసం అంటే ఏమిటి?",
      "options": [
        {
          "key": "A",
          "text": "రెండు లేదా అంతకంటే ఎక్కువ పదాలు కలసి ఒక సంక్షిప్త పదం కావడం"
        },
        {
          "key": "B",
          "text": "పదం చివర విభక్తి చేరడం"
        },
        {
          "key": "C",
          "text": "ఒకే అక్షరం పునరావృతం కావడం"
        },
        {
          "key": "D",
          "text": "వాక్యం ప్రశ్నగా మారడం"
        }
      ],
      "correctAnswer": "A",
      "explanation": "అర్థ సంబంధం ఉన్న పదాలు కలసి సంక్షిప్తంగా ఒక పదరూపం పొందడాన్ని సమాసం అంటారు."
    },
    {
      "id": "q25",
      "sectionId": "telugu",
      "globalIndex": 24,
      "text": "తత్పురుష సమాసంలో సాధారణంగా ఏది ప్రధానంగా ఉంటుంది?",
      "options": [
        {
          "key": "A",
          "text": "తరువాతి పదార్థం"
        },
        {
          "key": "B",
          "text": "రెండు పదాలు సమానంగా మాత్రమే"
        },
        {
          "key": "C",
          "text": "బయట ఉన్న మూడవ వ్యక్తి మాత్రమే"
        },
        {
          "key": "D",
          "text": "సంఖ్య మాత్రమే"
        }
      ],
      "correctAnswer": "A",
      "explanation": "తత్పురుష సమాసంలో ఉత్తరపదం ప్రధానంగా ఉండి ముందున్న పదం దానితో సంబంధం చూపుతుంది."
    },
    {
      "id": "q26",
      "sectionId": "telugu",
      "globalIndex": 25,
      "text": "కర్మధారయ సమాసం ఏ సంబంధాన్ని ఎక్కువగా చూపుతుంది?",
      "options": [
        {
          "key": "A",
          "text": "విశేషణం మరియు విశేష్యం"
        },
        {
          "key": "B",
          "text": "కేవలం సంఖ్య మరియు సమూహం"
        },
        {
          "key": "C",
          "text": "రెండు క్రియలు"
        },
        {
          "key": "D",
          "text": "సంబోధన మాత్రమే"
        }
      ],
      "correctAnswer": "A",
      "explanation": "కర్మధారయంలో ఒక పదం మరొక పదాన్ని విశేషణంలా వివరించి ఒకే వస్తువును సూచిస్తుంది."
    },
    {
      "id": "q27",
      "sectionId": "telugu",
      "globalIndex": 26,
      "text": "ద్వంద్వ సమాసంలో పదాల స్థితి ఎలా ఉంటుంది?",
      "options": [
        {
          "key": "A",
          "text": "రెండూ సమాన ప్రాధాన్యం కలిగి ఉంటాయి"
        },
        {
          "key": "B",
          "text": "మొదటి పదం మాత్రమే అర్థవంతం"
        },
        {
          "key": "C",
          "text": "రెండవ పదం ఉండదు"
        },
        {
          "key": "D",
          "text": "సంఖ్య మాత్రమే ప్రధానంగా ఉంటుంది"
        }
      ],
      "correctAnswer": "A",
      "explanation": "ద్వంద్వ సమాసంలో రెండు పదాలకూ సమాన ప్రాధాన్యం ఉండి కలిపి సమూహ భావం వస్తుంది."
    },
    {
      "id": "q28",
      "sectionId": "telugu",
      "globalIndex": 27,
      "text": "బహువ్రీహి సమాసం ప్రత్యేకత ఏమిటి?",
      "options": [
        {
          "key": "A",
          "text": "సమాసంలోని పదాలు కాకుండా బయట ఉన్న వ్యక్తి లేదా వస్తువును సూచిస్తుంది"
        },
        {
          "key": "B",
          "text": "ఎల్లప్పుడూ సంఖ్యను మాత్రమే సూచిస్తుంది"
        },
        {
          "key": "C",
          "text": "కేవలం రెండు స్వరాల కలయిక"
        },
        {
          "key": "D",
          "text": "విభక్తి చిహ్నం మాత్రమే"
        }
      ],
      "correctAnswer": "A",
      "explanation": "బహువ్రీహి సమాసం లోపలి పదార్థం ద్వారా బయట ఉన్న అధికారి లేదా వస్తువును సూచిస్తుంది."
    },
    {
      "id": "q29",
      "sectionId": "telugu",
      "globalIndex": 28,
      "text": "\"పంచపాత్రలు\" అనే పదం ఏ సమాసానికి దగ్గర ఉదాహరణ?",
      "options": [
        {
          "key": "A",
          "text": "ద్విగు సమాసం"
        },
        {
          "key": "B",
          "text": "బహువ్రీహి సమాసం"
        },
        {
          "key": "C",
          "text": "అవ్యయీభావ సమాసం"
        },
        {
          "key": "D",
          "text": "కర్మధారయ సమాసం"
        }
      ],
      "correctAnswer": "A",
      "explanation": "సంఖ్యాపూర్వక పదం సమూహ భావాన్ని తెలుపుతున్నందున ఇది ద్విగు సమాసానికి దగ్గర ఉదాహరణ."
    },
    {
      "id": "q30",
      "sectionId": "telugu",
      "globalIndex": 29,
      "text": "సంధి మరియు సమాసం మధ్య ప్రధాన తేడా ఏది?",
      "options": [
        {
          "key": "A",
          "text": "సంధి ధ్వని మార్పు; సమాసం అర్థ సంబంధం గల పదాల సంక్షిప్త కలయిక"
        },
        {
          "key": "B",
          "text": "సంధి ఎప్పుడూ సంఖ్య; సమాసం ఎప్పుడూ స్వరం"
        },
        {
          "key": "C",
          "text": "రెండూ ఒకే ప్రక్రియ; తేడా లేదు"
        },
        {
          "key": "D",
          "text": "సమాసం కేవలం అక్షర దోషం"
        }
      ],
      "correctAnswer": "A",
      "explanation": "సంధిలో ధ్వనుల కలయిక, మార్పు ముఖ్యం; సమాసంలో పదాల అర్థ సంబంధం మరియు సంక్షిప్త రూపం ముఖ్యం."
    }
  ]
}
